README.md
description.md
setup.py
atp/__init__.py
atp/cli.py
atp/common_read_write.py
atp/def_report.xlsx
atp/exec_testcase.py
atp/server.py
atp/server_run.py
atp/example/x_sweetest_example.zip
x_atp_cli.egg-info/PKG-INFO
x_atp_cli.egg-info/SOURCES.txt
x_atp_cli.egg-info/dependency_links.txt
x_atp_cli.egg-info/entry_points.txt
x_atp_cli.egg-info/requires.txt
x_atp_cli.egg-info/top_level.txt
x_sweetest/__init__.py
x_sweetest/autotest.py
x_sweetest/config.py
x_sweetest/data.py
x_sweetest/database.py
x_sweetest/elements.py
x_sweetest/globals.py
x_sweetest/junit.py
x_sweetest/locator.py
x_sweetest/log.py
x_sweetest/parse.py
x_sweetest/report.py
x_sweetest/snapshot.py
x_sweetest/testcase.py
x_sweetest/testsuite.py
x_sweetest/utility.py
x_sweetest/windows.py
x_sweetest/keywords/__init__.py
x_sweetest/keywords/common.py
x_sweetest/keywords/files.py
x_sweetest/keywords/http.py
x_sweetest/keywords/mobile.py
x_sweetest/keywords/web.py
x_sweetest/keywords/windows.py
x_sweetest/lib/__init__.py
x_sweetest/lib/c.py
x_sweetest/lib/http_handle.py
x_sweetest/lib/u.py