Metadata-Version: 2.1
Name: x-atp-cli
Version: 0.4.1
Summary: X automated test platform command line client
Home-page: https://github.com/hekaiyou/x-atp-cli
Author: HeKaiYou
Author-email: hekaiyou@gmail.com
License: UNKNOWN
Keywords: x,atp,test,platform
Platform: any
Classifier: Programming Language :: Python :: 3
Classifier: License :: OSI Approved :: MIT License
Classifier: Operating System :: OS Independent
